{
  "OvEpHeader": {
    "generated": "2024-06-09T17:50:00.271265176+02:00",
    "ov_vl_id": 395,
    "ov_nvv_id": 445,
    "ep_vl_id": 396,
    "ep_nvv_id": 446
  },
  "data": {
    "maz": "02",
    "taz": "219",
    "letszam": {
      "onkAtjelBelf": 1,
      "onkLakcSzavkorSzavaz": 94,
      "onkVpSzumma": 95,
      "onkMagyarAllampolgMagyarCim": 80,
      "onkMasEuAllampolg": 15,
      "onkBevLetMen": 0,
      "onkInduloVpSzumma": 95,
      "onkInduloMagyarAllampolgMagyarCim": 80,
      "onkInduloMasEuAllampolg": 15,
      "onkInduloBevLetMen": 0,
      "epVpSzumma": 83,
      "epMagyarAllampolgMagyarCim": 81,
      "epMasEuAllampolg": 2,
      "epInduloMagyarAllampolgMagyarCim": 80,
      "epInduloMasEuAllampolg": 0,
      "epInduloVpSzumma": 80
    },
    "mandatumok": {
      "egyeniListas": 4,
      "osszesen": 5
    },
    "egyeniJeloltek": [
      {
        "ej_id": 107098,
        "valaltip": "3",
        "kpn_id": 3803351,
        "maz": "02",
        "taz": "219",
        "sorsolt_sorsz": 1,
        "szavlap_sorsz": 1,
        "neve": "NÉMETHNÉ KOVÁCS ILDIKÓ",
        "jlcs_kod": 0,
        "jelolo_szervezetek": [
          0
        ],
        "jlcs_nev": "Független",
        "allapot": "1",
        "allapot_valt": "2024-04-29T00:00:00+02:00"
      },
      {
        "ej_id": 108717,
        "valaltip": "3",
        "kpn_id": 4408014,
        "maz": "02",
        "taz": "219",
        "sorsolt_sorsz": 2,
        "szavlap_sorsz": 2,
        "neve": "STANITZ JÁNOS EDÉNÉ",
        "jlcs_kod": 0,
        "jelolo_szervezetek": [
          0
        ],
        "jlcs_nev": "Független",
        "allapot": "1",
        "allapot_valt": "2024-04-29T00:00:00+02:00"
      },
      {
        "ej_id": 117190,
        "valaltip": "3",
        "kpn_id": 1823995,
        "maz": "02",
        "taz": "219",
        "sorsolt_sorsz": 3,
        "szavlap_sorsz": 3,
        "neve": "RIKKER FERENC",
        "jlcs_kod": 0,
        "jelolo_szervezetek": [
          0
        ],
        "jlcs_nev": "Független",
        "allapot": "1",
        "allapot_valt": "2024-04-29T00:00:00+02:00"
      },
      {
        "ej_id": 106220,
        "valaltip": "3",
        "kpn_id": 3516825,
        "maz": "02",
        "taz": "219",
        "sorsolt_sorsz": 4,
        "szavlap_sorsz": 4,
        "neve": "BŐSZ IMRE",
        "jlcs_kod": 0,
        "jelolo_szervezetek": [
          0
        ],
        "jlcs_nev": "Független",
        "allapot": "1",
        "allapot_valt": "2024-04-29T00:00:00+02:00"
      },
      {
        "ej_id": 121163,
        "valaltip": "1",
        "kpn_id": 2211608,
        "maz": "02",
        "taz": "219",
        "szavlap_sorsz": 1,
        "neve": "RUMSZAUER ILONA",
        "jlcs_kod": 0,
        "jelolo_szervezetek": [
          0
        ],
        "jlcs_nev": "Független",
        "allapot": "1",
        "allapot_valt": "2024-05-09T00:00:00+02:00"
      }
    ]
  }
}