{
  "OvEpHeader": {
    "generated": "2024-06-09T17:50:00.271265176+02:00",
    "ov_vl_id": 395,
    "ov_nvv_id": 445,
    "ep_vl_id": 396,
    "ep_nvv_id": 446
  },
  "data": {
    "maz": "07",
    "taz": "081",
    "letszam": {
      "onkAtjelBelf": 3,
      "onkLakcSzavkorSzavaz": 1798,
      "onkVpSzumma": 1801,
      "onkMagyarAllampolgMagyarCim": 1793,
      "onkMasEuAllampolg": 8,
      "onkBevLetMen": 0,
      "onkInduloVpSzumma": 1814,
      "onkInduloMagyarAllampolgMagyarCim": 1806,
      "onkInduloMasEuAllampolg": 8,
      "onkInduloBevLetMen": 0,
      "epVpSzumma": 1786,
      "epMagyarAllampolgMagyarCim": 1786,
      "epMasEuAllampolg": 0,
      "epInduloMagyarAllampolgMagyarCim": 1806,
      "epInduloMasEuAllampolg": 0,
      "epInduloVpSzumma": 1806
    },
    "mandatumok": {
      "egyeniListas": 6,
      "osszesen": 7
    },
    "egyeniJeloltek": [
      {
        "ej_id": 97985,
        "valaltip": "1",
        "kpn_id": 8164875,
        "maz": "07",
        "taz": "081",
        "sorsolt_sorsz": 1,
        "szavlap_sorsz": 1,
        "neve": "CSUTINÉ TURI IBOLYA",
        "jlcs_kod": 0,
        "jelolo_szervezetek": [
          0
        ],
        "jlcs_nev": "Független",
        "allapot": "1",
        "allapot_valt": "2024-05-09T00:00:00+02:00"
      },
      {
        "ej_id": 89540,
        "valaltip": "3",
        "kpn_id": 4847004,
        "maz": "07",
        "taz": "081",
        "sorsolt_sorsz": 1,
        "szavlap_sorsz": 1,
        "neve": "MOLNÁR-NAGY ISTVÁN",
        "jlcs_kod": 0,
        "jelolo_szervezetek": [
          0
        ],
        "jlcs_nev": "Független",
        "allapot": "1",
        "allapot_valt": "2024-04-30T00:00:00+02:00"
      },
      {
        "ej_id": 92509,
        "valaltip": "1",
        "kpn_id": 331566,
        "maz": "07",
        "taz": "081",
        "sorsolt_sorsz": 2,
        "szavlap_sorsz": 2,
        "neve": "GALLAI FERENC",
        "jlcs_kod": 0,
        "jelolo_szervezetek": [
          0
        ],
        "jlcs_nev": "Független",
        "allapot": "1",
        "allapot_valt": "2024-05-09T00:00:00+02:00"
      },
      {
        "ej_id": 117629,
        "valaltip": "3",
        "kpn_id": 1807593,
        "maz": "07",
        "taz": "081",
        "sorsolt_sorsz": 2,
        "szavlap_sorsz": 2,
        "neve": "HUSZTI NÁNDOR",
        "jlcs_kod": 0,
        "jelolo_szervezetek": [
          0
        ],
        "jlcs_nev": "Független",
        "allapot": "1",
        "allapot_valt": "2024-04-30T00:00:00+02:00"
      },
      {
        "ej_id": 102616,
        "valaltip": "3",
        "kpn_id": 1893563,
        "maz": "07",
        "taz": "081",
        "sorsolt_sorsz": 3,
        "szavlap_sorsz": 3,
        "neve": "POLÁNYI KLÁRA",
        "jlcs_kod": 0,
        "jelolo_szervezetek": [
          0
        ],
        "jlcs_nev": "Független",
        "allapot": "1",
        "allapot_valt": "2024-05-09T00:00:00+02:00"
      },
      {
        "ej_id": 92884,
        "valaltip": "3",
        "kpn_id": 9222362,
        "maz": "07",
        "taz": "081",
        "sorsolt_sorsz": 4,
        "szavlap_sorsz": 4,
        "neve": "RUDNICZAI RUDOLF",
        "jlcs_kod": 0,
        "jelolo_szervezetek": [
          0
        ],
        "jlcs_nev": "Független",
        "allapot": "1",
        "allapot_valt": "2024-05-09T00:00:00+02:00"
      },
      {
        "ej_id": 131135,
        "valaltip": "3",
        "kpn_id": 5065422,
        "maz": "07",
        "taz": "081",
        "sorsolt_sorsz": 5,
        "szavlap_sorsz": 5,
        "neve": "HOLL PÉTER",
        "jlcs_kod": 0,
        "jelolo_szervezetek": [
          0
        ],
        "jlcs_nev": "Független",
        "allapot": "1",
        "allapot_valt": "2024-05-09T00:00:00+02:00"
      },
      {
        "ej_id": 126030,
        "valaltip": "3",
        "kpn_id": 2584284,
        "maz": "07",
        "taz": "081",
        "sorsolt_sorsz": 6,
        "szavlap_sorsz": 6,
        "neve": "NYÁRI FERENCNÉ",
        "jlcs_kod": 0,
        "jelolo_szervezetek": [
          0
        ],
        "jlcs_nev": "Független",
        "allapot": "1",
        "allapot_valt": "2024-05-09T00:00:00+02:00"
      },
      {
        "ej_id": 96341,
        "valaltip": "3",
        "kpn_id": 1933714,
        "maz": "07",
        "taz": "081",
        "sorsolt_sorsz": 7,
        "szavlap_sorsz": 7,
        "neve": "NAGY LAJOS",
        "jlcs_kod": 0,
        "jelolo_szervezetek": [
          0
        ],
        "jlcs_nev": "Független",
        "allapot": "1",
        "allapot_valt": "2024-05-09T00:00:00+02:00"
      },
      {
        "ej_id": 107297,
        "valaltip": "3",
        "kpn_id": 701560,
        "maz": "07",
        "taz": "081",
        "sorsolt_sorsz": 8,
        "szavlap_sorsz": 8,
        "neve": "HUSZTI ELEMÉRNÉ",
        "jlcs_kod": 0,
        "jelolo_szervezetek": [
          0
        ],
        "jlcs_nev": "Független",
        "allapot": "1",
        "allapot_valt": "2024-04-30T00:00:00+02:00"
      },
      {
        "ej_id": 101626,
        "valaltip": "3",
        "kpn_id": 102996,
        "maz": "07",
        "taz": "081",
        "sorsolt_sorsz": 9,
        "szavlap_sorsz": 9,
        "neve": "KOVÁCS KATALIN",
        "jlcs_kod": 0,
        "jelolo_szervezetek": [
          0
        ],
        "jlcs_nev": "Független",
        "allapot": "1",
        "allapot_valt": "2024-05-09T00:00:00+02:00"
      },
      {
        "ej_id": 115977,
        "valaltip": "3",
        "kpn_id": 5719558,
        "maz": "07",
        "taz": "081",
        "sorsolt_sorsz": 10,
        "szavlap_sorsz": 10,
        "neve": "KOVÁCS GYÖRGYNÉ",
        "jlcs_kod": 0,
        "jelolo_szervezetek": [
          0
        ],
        "jlcs_nev": "Független",
        "allapot": "1",
        "allapot_valt": "2024-05-09T00:00:00+02:00"
      },
      {
        "ej_id": 111873,
        "valaltip": "3",
        "kpn_id": 5323339,
        "maz": "07",
        "taz": "081",
        "sorsolt_sorsz": 11,
        "szavlap_sorsz": 11,
        "neve": "ECSEKI GYÖRGY",
        "jlcs_kod": 0,
        "jelolo_szervezetek": [
          0
        ],
        "jlcs_nev": "Független",
        "allapot": "1",
        "allapot_valt": "2024-05-09T00:00:00+02:00"
      },
      {
        "ej_id": 126175,
        "valaltip": "3",
        "kpn_id": 2370793,
        "maz": "07",
        "taz": "081",
        "sorsolt_sorsz": 12,
        "szavlap_sorsz": 12,
        "neve": "NAGY ANDRÁS BOTOND",
        "jlcs_kod": 0,
        "jelolo_szervezetek": [
          0
        ],
        "jlcs_nev": "Független",
        "allapot": "1",
        "allapot_valt": "2024-05-09T00:00:00+02:00"
      },
      {
        "ej_id": 123251,
        "valaltip": "3",
        "kpn_id": 941817,
        "maz": "07",
        "taz": "081",
        "sorsolt_sorsz": 13,
        "szavlap_sorsz": 13,
        "neve": "NÉMETH LÁSZLÓ",
        "jlcs_kod": 0,
        "jelolo_szervezetek": [
          0
        ],
        "jlcs_nev": "Független",
        "allapot": "1",
        "allapot_valt": "2024-05-09T00:00:00+02:00"
      },
      {
        "ej_id": 101461,
        "valaltip": "3",
        "kpn_id": 7121198,
        "maz": "07",
        "taz": "081",
        "sorsolt_sorsz": 14,
        "szavlap_sorsz": 14,
        "neve": "BALASNÉ PÁL ANITA",
        "jlcs_kod": 0,
        "jelolo_szervezetek": [
          0
        ],
        "jlcs_nev": "Független",
        "allapot": "1",
        "allapot_valt": "2024-05-09T00:00:00+02:00"
      },
      {
        "ej_id": 90726,
        "valaltip": "3",
        "kpn_id": 5927032,
        "maz": "07",
        "taz": "081",
        "sorsolt_sorsz": 15,
        "szavlap_sorsz": 15,
        "neve": "NÉMETH ISTVÁN",
        "jlcs_kod": 2700,
        "jelolo_szervezetek": [
          1155
        ],
        "jlcs_nev": "CiKöSz",
        "allapot": "1",
        "allapot_valt": "2024-04-28T00:00:00+02:00"
      },
      {
        "ej_id": 128655,
        "valaltip": "3",
        "kpn_id": 3269435,
        "maz": "07",
        "taz": "081",
        "sorsolt_sorsz": 16,
        "szavlap_sorsz": 16,
        "neve": "HUSZTI JÓZSEF",
        "jlcs_kod": 0,
        "jelolo_szervezetek": [
          0
        ],
        "jlcs_nev": "Független",
        "allapot": "1",
        "allapot_valt": "2024-05-09T00:00:00+02:00"
      },
      {
        "ej_id": 129527,
        "valaltip": "3",
        "kpn_id": 1983938,
        "maz": "07",
        "taz": "081",
        "neve": "LENCSÉS NORBERT",
        "jlcs_kod": 0,
        "jelolo_szervezetek": [
          0
        ],
        "jlcs_nev": "Független",
        "allapot": "15",
        "allapot_valt": "2024-05-06T00:00:00+02:00"
      },
      {
        "ej_id": 129559,
        "valaltip": "3",
        "kpn_id": 9386575,
        "maz": "07",
        "taz": "081",
        "neve": "OLÁH BENCE ISTVÁN",
        "jlcs_kod": 0,
        "jelolo_szervezetek": [
          0
        ],
        "jlcs_nev": "Független",
        "allapot": "15",
        "allapot_valt": "2024-05-06T00:00:00+02:00"
      }
    ]
  }
}