{
  "OvEpHeader": {
    "generated": "2024-06-09T17:50:00.271265176+02:00",
    "ov_vl_id": 395,
    "ov_nvv_id": 445,
    "ep_vl_id": 396,
    "ep_nvv_id": 446
  },
  "data": {
    "maz": "16",
    "taz": "219",
    "letszam": {
      "onkAtjelBelf": 16,
      "onkLakcSzavkorSzavaz": 2689,
      "onkVpSzumma": 2705,
      "onkMagyarAllampolgMagyarCim": 2698,
      "onkMasEuAllampolg": 7,
      "onkBevLetMen": 0,
      "onkInduloVpSzumma": 2720,
      "onkInduloMagyarAllampolgMagyarCim": 2713,
      "onkInduloMasEuAllampolg": 7,
      "onkInduloBevLetMen": 0,
      "epVpSzumma": 2699,
      "epMagyarAllampolgMagyarCim": 2699,
      "epMasEuAllampolg": 0,
      "epInduloMagyarAllampolgMagyarCim": 2713,
      "epInduloMasEuAllampolg": 0,
      "epInduloVpSzumma": 2713
    },
    "mandatumok": {
      "egyeniListas": 6,
      "osszesen": 7
    },
    "egyeniJeloltek": [
      {
        "ej_id": 107252,
        "valaltip": "3",
        "kpn_id": 1507326,
        "maz": "16",
        "taz": "219",
        "sorsolt_sorsz": 1,
        "szavlap_sorsz": 1,
        "neve": "REVICZKI LAJOS",
        "jlcs_kod": 0,
        "jelolo_szervezetek": [
          0
        ],
        "jlcs_nev": "Független",
        "allapot": "1",
        "allapot_valt": "2024-04-29T00:00:00+02:00"
      },
      {
        "ej_id": 91059,
        "valaltip": "1",
        "kpn_id": 5794854,
        "maz": "16",
        "taz": "219",
        "sorsolt_sorsz": 1,
        "szavlap_sorsz": 1,
        "neve": "TÓTH ZITA",
        "fenykep": 26455,
        "kep_tipus": "JPG",
        "jlcs_kod": 0,
        "jelolo_szervezetek": [
          0
        ],
        "jlcs_nev": "Független",
        "allapot": "1",
        "allapot_valt": "2024-05-06T00:00:00+02:00"
      },
      {
        "ej_id": 80188,
        "valaltip": "1",
        "kpn_id": 4925548,
        "maz": "16",
        "taz": "219",
        "sorsolt_sorsz": 2,
        "szavlap_sorsz": 2,
        "neve": "TISZA SÁNDOR RAJMUND",
        "fenykep": 18480,
        "kep_tipus": "JPG",
        "jlcs_kod": 3111,
        "jelolo_szervezetek": [
          1076,
          1078
        ],
        "jlcs_nev": "FIDESZ-KDNP",
        "allapot": "1",
        "allapot_valt": "2024-04-27T00:00:00+02:00"
      },
      {
        "ej_id": 91270,
        "valaltip": "3",
        "kpn_id": 5794854,
        "maz": "16",
        "taz": "219",
        "sorsolt_sorsz": 2,
        "szavlap_sorsz": 2,
        "neve": "TÓTH ZITA",
        "fenykep": 26455,
        "kep_tipus": "JPG",
        "jlcs_kod": 0,
        "jelolo_szervezetek": [
          0
        ],
        "jlcs_nev": "Független",
        "allapot": "1",
        "allapot_valt": "2024-05-06T00:00:00+02:00"
      },
      {
        "ej_id": 110664,
        "valaltip": "3",
        "kpn_id": 7011546,
        "maz": "16",
        "taz": "219",
        "sorsolt_sorsz": 3,
        "szavlap_sorsz": 3,
        "neve": "TAMÁSI MARGIT",
        "jlcs_kod": 0,
        "jelolo_szervezetek": [
          0
        ],
        "jlcs_nev": "Független",
        "allapot": "1",
        "allapot_valt": "2024-05-06T00:00:00+02:00"
      },
      {
        "ej_id": 90419,
        "valaltip": "3",
        "kpn_id": 2494046,
        "maz": "16",
        "taz": "219",
        "sorsolt_sorsz": 4,
        "szavlap_sorsz": 4,
        "neve": "BÁLINT NORBERT",
        "jlcs_kod": 0,
        "jelolo_szervezetek": [
          0
        ],
        "jlcs_nev": "Független",
        "allapot": "1",
        "allapot_valt": "2024-04-27T00:00:00+02:00"
      },
      {
        "ej_id": 82321,
        "valaltip": "3",
        "kpn_id": 458414,
        "maz": "16",
        "taz": "219",
        "sorsolt_sorsz": 5,
        "szavlap_sorsz": 5,
        "neve": "HARSÁNYI IMRE",
        "jlcs_kod": 3111,
        "jelolo_szervezetek": [
          1076,
          1078
        ],
        "jlcs_nev": "FIDESZ-KDNP",
        "allapot": "1",
        "allapot_valt": "2024-04-27T00:00:00+02:00"
      },
      {
        "ej_id": 90618,
        "valaltip": "3",
        "kpn_id": 5658380,
        "maz": "16",
        "taz": "219",
        "sorsolt_sorsz": 6,
        "szavlap_sorsz": 6,
        "neve": "SZÉKELY ISTVÁN",
        "jlcs_kod": 0,
        "jelolo_szervezetek": [
          0
        ],
        "jlcs_nev": "Független",
        "allapot": "1",
        "allapot_valt": "2024-05-06T00:00:00+02:00"
      },
      {
        "ej_id": 121271,
        "valaltip": "3",
        "kpn_id": 3113734,
        "maz": "16",
        "taz": "219",
        "sorsolt_sorsz": 7,
        "szavlap_sorsz": 7,
        "neve": "SIMON-HORVÁTH ÁGNES",
        "fenykep": 26454,
        "kep_tipus": "JPG",
        "jlcs_kod": 0,
        "jelolo_szervezetek": [
          0
        ],
        "jlcs_nev": "Független",
        "allapot": "1",
        "allapot_valt": "2024-05-03T00:00:00+02:00"
      },
      {
        "ej_id": 88700,
        "valaltip": "3",
        "kpn_id": 3181704,
        "maz": "16",
        "taz": "219",
        "sorsolt_sorsz": 8,
        "szavlap_sorsz": 8,
        "neve": "STEFÁN JÓZSEF",
        "fenykep": 21231,
        "kep_tipus": "JPG",
        "jlcs_kod": 0,
        "jelolo_szervezetek": [
          0
        ],
        "jlcs_nev": "Független",
        "allapot": "1",
        "allapot_valt": "2024-04-27T00:00:00+02:00"
      },
      {
        "ej_id": 98826,
        "valaltip": "3",
        "kpn_id": 5374482,
        "maz": "16",
        "taz": "219",
        "sorsolt_sorsz": 9,
        "szavlap_sorsz": 9,
        "neve": "FARKAS GYŐZŐNÉ",
        "fenykep": 23117,
        "kep_tipus": "JPG",
        "jlcs_kod": 0,
        "jelolo_szervezetek": [
          0
        ],
        "jlcs_nev": "Független",
        "allapot": "1",
        "allapot_valt": "2024-04-29T00:00:00+02:00"
      },
      {
        "ej_id": 130456,
        "valaltip": "3",
        "kpn_id": 2739525,
        "maz": "16",
        "taz": "219",
        "sorsolt_sorsz": 10,
        "szavlap_sorsz": 10,
        "neve": "TISZA ANDRÁSNÉ",
        "jlcs_kod": 0,
        "jelolo_szervezetek": [
          0
        ],
        "jlcs_nev": "Független",
        "allapot": "1",
        "allapot_valt": "2024-05-09T00:00:00+02:00"
      },
      {
        "ej_id": 89134,
        "valaltip": "3",
        "kpn_id": 6712222,
        "maz": "16",
        "taz": "219",
        "sorsolt_sorsz": 11,
        "szavlap_sorsz": 11,
        "neve": "TISZA BENEDEK",
        "fenykep": 24404,
        "kep_tipus": "JPEG",
        "jlcs_kod": 0,
        "jelolo_szervezetek": [
          0
        ],
        "jlcs_nev": "Független",
        "allapot": "1",
        "allapot_valt": "2024-04-27T00:00:00+02:00"
      },
      {
        "ej_id": 97516,
        "valaltip": "3",
        "kpn_id": 3500520,
        "maz": "16",
        "taz": "219",
        "sorsolt_sorsz": 12,
        "szavlap_sorsz": 12,
        "neve": "GÁSPÁR BÉLA",
        "jlcs_kod": 0,
        "jelolo_szervezetek": [
          0
        ],
        "jlcs_nev": "Független",
        "allapot": "1",
        "allapot_valt": "2024-04-27T00:00:00+02:00"
      },
      {
        "ej_id": 89860,
        "valaltip": "3",
        "kpn_id": 4279260,
        "maz": "16",
        "taz": "219",
        "sorsolt_sorsz": 13,
        "szavlap_sorsz": 13,
        "neve": "DUDÁS KITTI",
        "jlcs_kod": 0,
        "jelolo_szervezetek": [
          0
        ],
        "jlcs_nev": "Független",
        "allapot": "1",
        "allapot_valt": "2024-04-27T00:00:00+02:00"
      },
      {
        "ej_id": 97340,
        "valaltip": "3",
        "kpn_id": 3195542,
        "maz": "16",
        "taz": "219",
        "sorsolt_sorsz": 14,
        "szavlap_sorsz": 14,
        "neve": "KISS TAMÁS",
        "fenykep": 20999,
        "kep_tipus": "JPG",
        "jlcs_kod": 0,
        "jelolo_szervezetek": [
          0
        ],
        "jlcs_nev": "Független",
        "allapot": "1",
        "allapot_valt": "2024-04-27T00:00:00+02:00"
      },
      {
        "ej_id": 102641,
        "valaltip": "3",
        "kpn_id": 1896806,
        "maz": "16",
        "taz": "219",
        "sorsolt_sorsz": 15,
        "szavlap_sorsz": 15,
        "neve": "KÓSA ATTILA",
        "jlcs_kod": 0,
        "jelolo_szervezetek": [
          0
        ],
        "jlcs_nev": "Független",
        "allapot": "1",
        "allapot_valt": "2024-04-27T00:00:00+02:00"
      },
      {
        "ej_id": 88434,
        "valaltip": "3",
        "kpn_id": 3925232,
        "maz": "16",
        "taz": "219",
        "sorsolt_sorsz": 16,
        "szavlap_sorsz": 16,
        "neve": "VELICSKÓ MIHÁLY",
        "fenykep": 20682,
        "kep_tipus": "JPG",
        "jlcs_kod": 0,
        "jelolo_szervezetek": [
          0
        ],
        "jlcs_nev": "Független",
        "allapot": "1",
        "allapot_valt": "2024-04-27T00:00:00+02:00"
      }
    ]
  }
}