{
  "OvEpHeader": {
    "generated": "2024-06-09T17:50:00.271265176+02:00",
    "ov_vl_id": 395,
    "ov_nvv_id": 445,
    "ep_vl_id": 396,
    "ep_nvv_id": 446
  },
  "data": {
    "maz": "04",
    "taz": "054",
    "korzethatarok": [
      {
        "szavkor": "002",
        "kt_nev": "Achim L.András",
        "kt_jelleg": "utca",
        "int_tip": "2"
      },
      {
        "szavkor": "002",
        "kt_nev": "Ady Endre",
        "kt_jelleg": "utca",
        "int_tip": "2"
      },
      {
        "szavkor": "001",
        "kt_nev": "Arany János",
        "kt_jelleg": "utca",
        "int_tip": "2"
      },
      {
        "szavkor": "002",
        "kt_nev": "Békési",
        "kt_jelleg": "utca",
        "int_tip": "2"
      },
      {
        "szavkor": "002",
        "kt_nev": "Bojtár",
        "kt_jelleg": "utca",
        "int_tip": "2"
      },
      {
        "szavkor": "001",
        "kt_nev": "Dózsa György",
        "kt_jelleg": "utca",
        "int_tip": "2"
      },
      {
        "szavkor": "002",
        "kt_nev": "Duna",
        "kt_jelleg": "utca",
        "int_tip": "2"
      },
      {
        "szavkor": "002",
        "kt_nev": "Földvári",
        "kt_jelleg": "utca",
        "int_tip": "3"
      },
      {
        "szavkor": "001",
        "kt_nev": "Földvári",
        "kt_jelleg": "utca",
        "int_tip": "4"
      },
      {
        "szavkor": "002",
        "kt_nev": "Honvéd",
        "kt_jelleg": "utca",
        "int_tip": "2"
      },
      {
        "szavkor": "002",
        "kt_nev": "Juhász",
        "kt_jelleg": "utca",
        "int_tip": "2"
      },
      {
        "szavkor": "001",
        "kt_nev": "Kossuth Lajos",
        "kt_jelleg": "utca",
        "int_tip": "2"
      },
      {
        "szavkor": "002",
        "kt_nev": "Köles",
        "kt_jelleg": "utca",
        "int_tip": "2"
      },
      {
        "szavkor": "001",
        "kt_nev": "Kőrösi Csoma Sándor",
        "kt_jelleg": "utca",
        "int_tip": "2"
      },
      {
        "szavkor": "001",
        "kt_nev": "Levendula",
        "kt_jelleg": "utca",
        "int_tip": "2"
      },
      {
        "szavkor": "002",
        "kt_nev": "Mokry",
        "kt_jelleg": "utca",
        "int_tip": "2"
      },
      {
        "szavkor": "002",
        "kt_nev": "Őrház",
        "kt_jelleg": "utca",
        "int_tip": "2"
      },
      {
        "szavkor": "002",
        "kt_nev": "Petőfi",
        "kt_jelleg": "utca",
        "int_tip": "2"
      },
      {
        "szavkor": "001",
        "kt_nev": "Rákóczi",
        "kt_jelleg": "utca",
        "int_tip": "2"
      },
      {
        "szavkor": "002",
        "kt_nev": "Rövid",
        "kt_jelleg": "utca",
        "int_tip": "2"
      },
      {
        "szavkor": "002",
        "kt_nev": "Szabó Dezső",
        "kt_jelleg": "utca",
        "int_tip": "2"
      },
      {
        "szavkor": "002",
        "kt_nev": "Szarvasi",
        "kt_jelleg": "utca",
        "int_tip": "2"
      },
      {
        "szavkor": "001",
        "kt_nev": "Szélső",
        "kt_jelleg": "utca",
        "int_tip": "2"
      },
      {
        "szavkor": "001",
        "kt_nev": "Tanya II.",
        "int_tip": "2"
      },
      {
        "szavkor": "001",
        "kt_nev": "Tanya III.",
        "int_tip": "2"
      },
      {
        "szavkor": "001",
        "kt_nev": "Tanya IV.",
        "int_tip": "2"
      },
      {
        "szavkor": "001",
        "kt_nev": "Tessedik",
        "kt_jelleg": "utca",
        "int_tip": "2"
      },
      {
        "szavkor": "002",
        "kt_nev": "Verseny",
        "kt_jelleg": "utca",
        "int_tip": "2"
      }
    ]
  }
}