{
  "OvEpHeader": {
    "generated": "2024-06-09T17:50:00.271265176+02:00",
    "ov_vl_id": 395,
    "ov_nvv_id": 445,
    "ep_vl_id": 396,
    "ep_nvv_id": 446
  },
  "data": {
    "maz": "14",
    "taz": "166",
    "korzethatarok": [
      {
        "szavkor": "001",
        "kt_nev": "Ady Endre",
        "kt_jelleg": "utca",
        "int_tip": "2"
      },
      {
        "szavkor": "004",
        "kt_nev": "Akácfa",
        "kt_jelleg": "utca",
        "int_tip": "2"
      },
      {
        "szavkor": "001",
        "kt_nev": "Alexandra Pavlovna",
        "kt_jelleg": "köz",
        "int_tip": "2"
      },
      {
        "szavkor": "002",
        "kt_nev": "Alkonyat",
        "kt_jelleg": "sétány",
        "int_tip": "2"
      },
      {
        "szavkor": "004",
        "kt_nev": "Árvalányhaj",
        "kt_jelleg": "utca",
        "int_tip": "2"
      },
      {
        "szavkor": "004",
        "kt_nev": "Asztalos",
        "kt_jelleg": "utca",
        "int_tip": "2"
      },
      {
        "szavkor": "002",
        "kt_nev": "Barackos",
        "kt_jelleg": "út",
        "int_tip": "2"
      },
      {
        "szavkor": "005",
        "kt_nev": "Batthyány",
        "kt_jelleg": "utca",
        "int_tip": "2"
      },
      {
        "szavkor": "004",
        "kt_nev": "Bécsi",
        "kt_jelleg": "út",
        "int_tip": "2"
      },
      {
        "szavkor": "005",
        "kt_nev": "Bem",
        "kt_jelleg": "utca",
        "int_tip": "2"
      },
      {
        "szavkor": "004",
        "kt_nev": "Berkenye",
        "kt_jelleg": "utca",
        "int_tip": "2"
      },
      {
        "szavkor": "002",
        "kt_nev": "Bimbó",
        "kt_jelleg": "utca",
        "int_tip": "2"
      },
      {
        "szavkor": "003",
        "kt_nev": "Bocskai",
        "kt_jelleg": "utca",
        "int_tip": "2"
      },
      {
        "szavkor": "005",
        "kt_nev": "Bodnár",
        "kt_jelleg": "utca",
        "int_tip": "2"
      },
      {
        "szavkor": "004",
        "kt_nev": "Boglárka",
        "kt_jelleg": "utca",
        "int_tip": "2"
      },
      {
        "szavkor": "002",
        "kt_nev": "Borostyán",
        "kt_jelleg": "köz",
        "int_tip": "2"
      },
      {
        "szavkor": "002",
        "kt_nev": "Borostyán",
        "kt_jelleg": "utca",
        "int_tip": "2"
      },
      {
        "szavkor": "003",
        "kt_nev": "Budai",
        "kt_jelleg": "út",
        "int_tip": "2"
      },
      {
        "szavkor": "002",
        "kt_nev": "Budakalászi",
        "kt_jelleg": "út",
        "int_tip": "2"
      },
      {
        "szavkor": "002",
        "kt_nev": "Búzavirág",
        "kt_jelleg": "utca",
        "int_tip": "2"
      },
      {
        "szavkor": "002",
        "kt_nev": "Bükkfa",
        "kt_jelleg": "utca",
        "int_tip": "2"
      },
      {
        "szavkor": "002",
        "kt_nev": "Cinege",
        "kt_jelleg": "utca",
        "int_tip": "2"
      },
      {
        "szavkor": "002",
        "kt_nev": "Cseresznyés",
        "kt_jelleg": "utca",
        "int_tip": "2"
      },
      {
        "szavkor": "001",
        "kt_nev": "Csillaghegyi",
        "kt_jelleg": "út",
        "int_tip": "2"
      },
      {
        "szavkor": "004",
        "kt_nev": "Csipkebogyó",
        "kt_jelleg": "utca",
        "int_tip": "2"
      },
      {
        "szavkor": "001",
        "kt_nev": "Csókavár",
        "kt_jelleg": "utca",
        "int_tip": "2"
      },
      {
        "szavkor": "003",
        "kt_nev": "Csoóri Sándor",
        "kt_jelleg": "utca",
        "int_tip": "2"
      },
      {
        "szavkor": "004",
        "kt_nev": "Damjanich",
        "kt_jelleg": "út",
        "int_tip": "2"
      },
      {
        "szavkor": "005",
        "kt_nev": "Deák Ferenc",
        "kt_jelleg": "utca",
        "int_tip": "2"
      },
      {
        "szavkor": "004",
        "kt_nev": "Dessewffy",
        "kt_jelleg": "utca",
        "int_tip": "2"
      },
      {
        "szavkor": "002",
        "kt_nev": "Diófa",
        "kt_jelleg": "utca",
        "int_tip": "2"
      },
      {
        "szavkor": "005",
        "kt_nev": "Doktor",
        "kt_jelleg": "utca",
        "int_tip": "2"
      },
      {
        "szavkor": "003",
        "kt_nev": "Dózsa György",
        "kt_jelleg": "út",
        "int_tip": "2"
      },
      {
        "szavkor": "003",
        "kt_nev": "Dr. Bodó Tibor",
        "kt_jelleg": "köz",
        "int_tip": "2"
      },
      {
        "szavkor": "002",
        "kt_nev": "Eper",
        "kt_jelleg": "utca",
        "int_tip": "2"
      },
      {
        "szavkor": "001",
        "kt_nev": "Ezüsthegy",
        "kt_jelleg": "utca",
        "int_tip": "2"
      },
      {
        "szavkor": "002",
        "kt_nev": "Fagyöngy",
        "kt_jelleg": "utca",
        "int_tip": "2"
      },
      {
        "szavkor": "005",
        "kt_nev": "Fenyves",
        "kt_jelleg": "sétány",
        "int_tip": "2"
      },
      {
        "szavkor": "005",
        "kt_nev": "Fenyves",
        "kt_jelleg": "utca",
        "int_tip": "2"
      },
      {
        "szavkor": "003",
        "kt_nev": "Fő",
        "kt_jelleg": "utca",
        "int_tip": "2"
      },
      {
        "szavkor": "002",
        "kt_nev": "Fülemüle",
        "kt_jelleg": "utca",
        "int_tip": "2"
      },
      {
        "szavkor": "004",
        "kt_nev": "Gábor Áron",
        "kt_jelleg": "sétány",
        "int_tip": "2"
      },
      {
        "szavkor": "002",
        "kt_nev": "Galagonya",
        "kt_jelleg": "köz",
        "int_tip": "2"
      },
      {
        "szavkor": "002",
        "kt_nev": "Gólyahír",
        "kt_jelleg": "utca",
        "int_tip": "2"
      },
      {
        "szavkor": "004",
        "kt_nev": "Görgey",
        "kt_jelleg": "utca",
        "int_tip": "2"
      },
      {
        "szavkor": "004",
        "kt_nev": "Gyűszűvirág",
        "kt_jelleg": "utca",
        "int_tip": "2"
      },
      {
        "szavkor": "002",
        "kt_nev": "Hársfa",
        "kt_jelleg": "utca",
        "int_tip": "2"
      },
      {
        "szavkor": "004",
        "kt_nev": "Határkő",
        "kt_jelleg": "utca",
        "int_tip": "2"
      },
      {
        "szavkor": "004",
        "kt_nev": "Hérics",
        "kt_jelleg": "utca",
        "int_tip": "2"
      },
      {
        "szavkor": "002",
        "kt_nev": "Holló",
        "kt_jelleg": "köz",
        "int_tip": "2"
      },
      {
        "szavkor": "001",
        "kt_nev": "Honvéd",
        "kt_jelleg": "utca",
        "int_tip": "2"
      },
      {
        "szavkor": "002",
        "kt_nev": "Hóvirág",
        "kt_jelleg": "utca",
        "int_tip": "2"
      },
      {
        "szavkor": "005",
        "kt_nev": "Huszár",
        "kt_jelleg": "utca",
        "int_tip": "2"
      },
      {
        "szavkor": "002",
        "kt_nev": "Ibolya",
        "kt_jelleg": "utca",
        "int_tip": "2"
      },
      {
        "szavkor": "003",
        "kt_nev": "Iskola",
        "kt_jelleg": "utca",
        "int_tip": "2"
      },
      {
        "szavkor": "002",
        "kt_nev": "Jókai",
        "kt_jelleg": "utca",
        "int_tip": "2"
      },
      {
        "szavkor": "001",
        "kt_nev": "József Attila",
        "kt_jelleg": "utca",
        "int_tip": "2"
      },
      {
        "szavkor": "004",
        "kt_nev": "József nádor",
        "kt_jelleg": "utca",
        "int_tip": "2"
      },
      {
        "szavkor": "004",
        "kt_nev": "Kakukkfű",
        "kt_jelleg": "utca",
        "int_tip": "2"
      },
      {
        "szavkor": "004",
        "kt_nev": "Kalmár",
        "kt_jelleg": "utca",
        "int_tip": "2"
      },
      {
        "szavkor": "004",
        "kt_nev": "Kálvária",
        "kt_jelleg": "utca",
        "int_tip": "2"
      },
      {
        "szavkor": "004",
        "kt_nev": "Kamilla",
        "kt_jelleg": "utca",
        "int_tip": "2"
      },
      {
        "szavkor": "002",
        "kt_nev": "Kankalin",
        "kt_jelleg": "utca",
        "int_tip": "2"
      },
      {
        "szavkor": "005",
        "kt_nev": "Kárókatona",
        "kt_jelleg": "utca",
        "int_tip": "2"
      },
      {
        "szavkor": "004",
        "kt_nev": "Kecskerágó",
        "kt_jelleg": "utca",
        "int_tip": "2"
      },
      {
        "szavkor": "003",
        "kt_nev": "Kert",
        "kt_jelleg": "utca",
        "int_tip": "2"
      },
      {
        "szavkor": "002",
        "kt_nev": "Kevély",
        "kt_jelleg": "utca",
        "int_tip": "2"
      },
      {
        "szavkor": "002",
        "kt_nev": "Kinizsi",
        "kt_jelleg": "utca",
        "int_tip": "2"
      },
      {
        "szavkor": "003",
        "kt_nev": "Kmety György",
        "kt_jelleg": "utca",
        "int_tip": "2"
      },
      {
        "szavkor": "002",
        "kt_nev": "Kócsag",
        "kt_jelleg": "utca",
        "int_tip": "2"
      },
      {
        "szavkor": "002",
        "kt_nev": "Kormorán",
        "kt_jelleg": "utca",
        "int_tip": "2"
      },
      {
        "szavkor": "003",
        "kt_nev": "Kossuth Lajos",
        "kt_jelleg": "utca",
        "int_tip": "2"
      },
      {
        "szavkor": "002",
        "kt_nev": "Kőbánya",
        "kt_jelleg": "utca",
        "int_tip": "2"
      },
      {
        "szavkor": "002",
        "kt_nev": "Kőhegy",
        "kt_jelleg": "utca",
        "int_tip": "2"
      },
      {
        "szavkor": "002",
        "kt_nev": "Kölcsey",
        "kt_jelleg": "utca",
        "int_tip": "2"
      },
      {
        "szavkor": "002",
        "kt_nev": "Körte",
        "kt_jelleg": "utca",
        "int_tip": "2"
      },
      {
        "szavkor": "004",
        "kt_nev": "Kövirózsa",
        "kt_jelleg": "utca",
        "int_tip": "2"
      },
      {
        "szavkor": "004",
        "kt_nev": "Levendula",
        "kt_jelleg": "utca",
        "int_tip": "2"
      },
      {
        "szavkor": "005",
        "kt_nev": "Lobogó",
        "kt_jelleg": "utca",
        "int_tip": "2"
      },
      {
        "szavkor": "005",
        "kt_nev": "Magyar",
        "kt_jelleg": "utca",
        "int_tip": "2"
      },
      {
        "szavkor": "003",
        "kt_nev": "Makkos",
        "kt_jelleg": "utca",
        "int_tip": "2"
      },
      {
        "szavkor": "002",
        "kt_nev": "Mandula",
        "kt_jelleg": "utca",
        "int_tip": "2"
      },
      {
        "szavkor": "003",
        "kt_nev": "Meggyes",
        "kt_jelleg": "utca",
        "int_tip": "2"
      },
      {
        "szavkor": "004",
        "kt_nev": "Mészégető",
        "kt_jelleg": "köz",
        "int_tip": "2"
      },
      {
        "szavkor": "004",
        "kt_nev": "Mészégető",
        "kt_jelleg": "utca",
        "int_tip": "2"
      },
      {
        "szavkor": "003",
        "kt_nev": "Muskáth György",
        "kt_jelleg": "utca",
        "int_tip": "2"
      },
      {
        "szavkor": "005",
        "kt_nev": "Must",
        "kt_jelleg": "utca",
        "int_tip": "2"
      },
      {
        "szavkor": "004",
        "kt_nev": "Nap",
        "kt_jelleg": "utca",
        "int_tip": "2"
      },
      {
        "szavkor": "004",
        "kt_nev": "Napraforgó",
        "kt_jelleg": "utca",
        "int_tip": "2"
      },
      {
        "szavkor": "005",
        "kt_nev": "Óbor",
        "kt_jelleg": "sétány",
        "int_tip": "2"
      },
      {
        "szavkor": "002",
        "kt_nev": "Óvoda",
        "kt_jelleg": "köz",
        "int_tip": "2"
      },
      {
        "szavkor": "002",
        "kt_nev": "Őzike",
        "kt_jelleg": "utca",
        "int_tip": "2"
      },
      {
        "szavkor": "005",
        "kt_nev": "Patak",
        "kt_jelleg": "utca",
        "int_tip": "2"
      },
      {
        "szavkor": "005",
        "kt_nev": "Péterhegyi",
        "kt_jelleg": "út",
        "int_tip": "2"
      },
      {
        "szavkor": "001",
        "kt_nev": "Petőfi Sándor",
        "kt_jelleg": "utca",
        "int_tip": "3"
      },
      {
        "szavkor": "002",
        "kt_nev": "Petőfi Sándor",
        "kt_jelleg": "utca",
        "int_tip": "4"
      },
      {
        "szavkor": "002",
        "kt_nev": "Pillangó",
        "kt_jelleg": "utca",
        "int_tip": "2"
      },
      {
        "szavkor": "002",
        "kt_nev": "Pipacs",
        "kt_jelleg": "utca",
        "int_tip": "2"
      },
      {
        "szavkor": "002",
        "kt_nev": "Platán",
        "kt_jelleg": "utca",
        "int_tip": "2"
      },
      {
        "szavkor": "005",
        "kt_nev": "Présház",
        "kt_jelleg": "utca",
        "int_tip": "2"
      },
      {
        "szavkor": "001",
        "kt_nev": "Radnóti Miklós",
        "kt_jelleg": "köz",
        "int_tip": "2"
      },
      {
        "szavkor": "001",
        "kt_nev": "Radnóti Miklós",
        "kt_jelleg": "utca",
        "int_tip": "2"
      },
      {
        "szavkor": "002",
        "kt_nev": "Rákóczi Ferenc",
        "kt_jelleg": "köz",
        "int_tip": "2"
      },
      {
        "szavkor": "002",
        "kt_nev": "Rákóczi Ferenc",
        "kt_jelleg": "utca",
        "int_tip": "2"
      },
      {
        "szavkor": "002",
        "kt_nev": "Régi",
        "kt_jelleg": "utca",
        "int_tip": "2"
      },
      {
        "szavkor": "002",
        "kt_nev": "Rézvirág",
        "kt_jelleg": "utca",
        "int_tip": "2"
      },
      {
        "szavkor": "002",
        "kt_nev": "Róka",
        "kt_jelleg": "köz",
        "int_tip": "2"
      },
      {
        "szavkor": "005",
        "kt_nev": "Rókahegyi",
        "kt_jelleg": "út",
        "int_tip": "2"
      },
      {
        "szavkor": "004",
        "kt_nev": "Rozmaring",
        "kt_jelleg": "utca",
        "int_tip": "2"
      },
      {
        "szavkor": "002",
        "kt_nev": "Rózsa",
        "kt_jelleg": "utca",
        "int_tip": "2"
      },
      {
        "szavkor": "002",
        "kt_nev": "Sadove",
        "kt_jelleg": "út",
        "int_tip": "2"
      },
      {
        "szavkor": "005",
        "kt_nev": "Sajtár",
        "kt_jelleg": "utca",
        "int_tip": "2"
      },
      {
        "szavkor": "001",
        "kt_nev": "Sport",
        "kt_jelleg": "köz",
        "int_tip": "2"
      },
      {
        "szavkor": "001",
        "kt_nev": "Sport",
        "kt_jelleg": "utca",
        "int_tip": "2"
      },
      {
        "szavkor": "005",
        "kt_nev": "Szamóca",
        "kt_jelleg": "utca",
        "int_tip": "2"
      },
      {
        "szavkor": "002",
        "kt_nev": "Szeder",
        "kt_jelleg": "köz",
        "int_tip": "2"
      },
      {
        "szavkor": "001",
        "kt_nev": "Szegfű",
        "kt_jelleg": "utca",
        "int_tip": "2"
      },
      {
        "szavkor": "004",
        "kt_nev": "Szikla",
        "kt_jelleg": "köz",
        "int_tip": "2"
      },
      {
        "szavkor": "004",
        "kt_nev": "Szikla",
        "kt_jelleg": "utca",
        "int_tip": "2"
      },
      {
        "szavkor": "002",
        "kt_nev": "Szilva",
        "kt_jelleg": "utca",
        "int_tip": "2"
      },
      {
        "szavkor": "002",
        "kt_nev": "Szirom",
        "kt_jelleg": "utca",
        "int_tip": "2"
      },
      {
        "szavkor": "005",
        "kt_nev": "Szőlőskert",
        "kt_jelleg": "utca",
        "int_tip": "2"
      },
      {
        "szavkor": "005",
        "kt_nev": "Táborföld",
        "kt_jelleg": "út",
        "int_tip": "2"
      },
      {
        "szavkor": "001",
        "kt_nev": "Táncsics Mihály",
        "kt_jelleg": "utca",
        "int_tip": "2"
      },
      {
        "szavkor": "002",
        "kt_nev": "Tátika",
        "kt_jelleg": "utca",
        "int_tip": "2"
      },
      {
        "szavkor": "003",
        "kt_nev": "Templom",
        "kt_jelleg": "tér",
        "int_tip": "2"
      },
      {
        "szavkor": "002",
        "kt_nev": "Tulipán",
        "kt_jelleg": "utca",
        "int_tip": "2"
      },
      {
        "szavkor": "004",
        "kt_nev": "Tücsök",
        "kt_jelleg": "köz",
        "int_tip": "2"
      },
      {
        "szavkor": "004",
        "kt_nev": "Tücsök",
        "kt_jelleg": "utca",
        "int_tip": "2"
      },
      {
        "szavkor": "004",
        "kt_nev": "Tüzér",
        "kt_jelleg": "utca",
        "int_tip": "2"
      },
      {
        "szavkor": "004",
        "kt_nev": "Ürömi",
        "kt_jelleg": "út",
        "int_tip": "2"
      },
      {
        "szavkor": "005",
        "kt_nev": "Vessző",
        "kt_jelleg": "utca",
        "int_tip": "2"
      },
      {
        "szavkor": "003",
        "kt_nev": "Völgyliget",
        "kt_jelleg": "sétány",
        "int_tip": "2"
      },
      {
        "szavkor": "002",
        "kt_nev": "Vörösbegy",
        "kt_jelleg": "utca",
        "int_tip": "2"
      }
    ]
  }
}