{
  "OvEpHeader": {
    "generated": "2024-06-09T17:50:00.271265176+02:00",
    "ov_vl_id": 395,
    "ov_nvv_id": 445,
    "ep_vl_id": 396,
    "ep_nvv_id": 446
  },
  "data": {
    "maz": "19",
    "taz": "178",
    "letszam": {
      "onkAtjelBelf": 10,
      "onkLakcSzavkorSzavaz": 177,
      "onkVpSzumma": 187,
      "onkMagyarAllampolgMagyarCim": 183,
      "onkMasEuAllampolg": 4,
      "onkBevLetMen": 0,
      "onkInduloVpSzumma": 181,
      "onkInduloMagyarAllampolgMagyarCim": 178,
      "onkInduloMasEuAllampolg": 3,
      "onkInduloBevLetMen": 0,
      "epVpSzumma": 188,
      "epMagyarAllampolgMagyarCim": 185,
      "epMasEuAllampolg": 3,
      "epInduloMagyarAllampolgMagyarCim": 178,
      "epInduloMasEuAllampolg": 1,
      "epInduloVpSzumma": 179
    },
    "mandatumok": {
      "egyeniListas": 4,
      "osszesen": 5
    },
    "egyeniJeloltek": [
      {
        "ej_id": 94898,
        "valaltip": "1",
        "kpn_id": 2537857,
        "maz": "19",
        "taz": "178",
        "sorsolt_sorsz": 1,
        "szavlap_sorsz": 1,
        "neve": "MEZEI JÁNOS",
        "fenykep": 26089,
        "kep_tipus": "JPG",
        "jlcs_kod": 0,
        "jelolo_szervezetek": [
          0
        ],
        "jlcs_nev": "Független",
        "allapot": "1",
        "allapot_valt": "2024-05-09T00:00:00+02:00"
      },
      {
        "ej_id": 109847,
        "valaltip": "3",
        "kpn_id": 4506227,
        "maz": "19",
        "taz": "178",
        "sorsolt_sorsz": 1,
        "szavlap_sorsz": 1,
        "neve": "SÁRVÁRI TAMÁS",
        "jlcs_kod": 0,
        "jelolo_szervezetek": [
          0
        ],
        "jlcs_nev": "Független",
        "allapot": "1",
        "allapot_valt": "2024-05-09T00:00:00+02:00"
      },
      {
        "ej_id": 94771,
        "valaltip": "3",
        "kpn_id": 2537857,
        "maz": "19",
        "taz": "178",
        "sorsolt_sorsz": 2,
        "szavlap_sorsz": 2,
        "neve": "MEZEI JÁNOS",
        "fenykep": 26089,
        "kep_tipus": "JPG",
        "jlcs_kod": 0,
        "jelolo_szervezetek": [
          0
        ],
        "jlcs_nev": "Független",
        "allapot": "1",
        "allapot_valt": "2024-05-09T00:00:00+02:00"
      },
      {
        "ej_id": 90118,
        "valaltip": "1",
        "kpn_id": 1422180,
        "maz": "19",
        "taz": "178",
        "sorsolt_sorsz": 2,
        "szavlap_sorsz": 2,
        "neve": "MOLNÁR KÁROLY",
        "jlcs_kod": 0,
        "jelolo_szervezetek": [
          0
        ],
        "jlcs_nev": "Független",
        "allapot": "1",
        "allapot_valt": "2024-05-06T00:00:00+02:00"
      },
      {
        "ej_id": 91479,
        "valaltip": "1",
        "kpn_id": 5796840,
        "maz": "19",
        "taz": "178",
        "sorsolt_sorsz": 3,
        "neve": "SÁRVÁRI CSABA",
        "jlcs_kod": 0,
        "jelolo_szervezetek": [
          0
        ],
        "jlcs_nev": "Független",
        "allapot": "33",
        "allapot_valt": "2024-05-13T00:00:00+02:00"
      },
      {
        "ej_id": 95752,
        "valaltip": "3",
        "kpn_id": 6154484,
        "maz": "19",
        "taz": "178",
        "sorsolt_sorsz": 3,
        "szavlap_sorsz": 3,
        "neve": "SÁRVÁRI NIKOLETT",
        "jlcs_kod": 0,
        "jelolo_szervezetek": [
          0
        ],
        "jlcs_nev": "Független",
        "allapot": "1",
        "allapot_valt": "2024-05-09T00:00:00+02:00"
      },
      {
        "ej_id": 95583,
        "valaltip": "1",
        "kpn_id": 3806094,
        "maz": "19",
        "taz": "178",
        "sorsolt_sorsz": 4,
        "szavlap_sorsz": 3,
        "neve": "ISTVÁNDI TAMÁS",
        "fenykep": 25725,
        "kep_tipus": "JPG",
        "jlcs_kod": 0,
        "jelolo_szervezetek": [
          0
        ],
        "jlcs_nev": "Független",
        "allapot": "1",
        "allapot_valt": "2024-05-09T00:00:00+02:00"
      },
      {
        "ej_id": 121878,
        "valaltip": "3",
        "kpn_id": 5197209,
        "maz": "19",
        "taz": "178",
        "sorsolt_sorsz": 4,
        "szavlap_sorsz": 4,
        "neve": "KOVÁCS LAJOS",
        "jlcs_kod": 0,
        "jelolo_szervezetek": [
          0
        ],
        "jlcs_nev": "Független",
        "allapot": "1",
        "allapot_valt": "2024-04-29T00:00:00+02:00"
      },
      {
        "ej_id": 114442,
        "valaltip": "3",
        "kpn_id": 210127,
        "maz": "19",
        "taz": "178",
        "sorsolt_sorsz": 5,
        "szavlap_sorsz": 5,
        "neve": "FARKAS MIKLÓS",
        "jlcs_kod": 0,
        "jelolo_szervezetek": [
          0
        ],
        "jlcs_nev": "Független",
        "allapot": "1",
        "allapot_valt": "2024-04-29T00:00:00+02:00"
      },
      {
        "ej_id": 119094,
        "valaltip": "3",
        "kpn_id": 2981729,
        "maz": "19",
        "taz": "178",
        "sorsolt_sorsz": 6,
        "szavlap_sorsz": 6,
        "neve": "TRÁJER ISTVÁNNÉ",
        "jlcs_kod": 0,
        "jelolo_szervezetek": [
          0
        ],
        "jlcs_nev": "Független",
        "allapot": "1",
        "allapot_valt": "2024-04-29T00:00:00+02:00"
      },
      {
        "ej_id": 119127,
        "valaltip": "3",
        "kpn_id": 4883014,
        "maz": "19",
        "taz": "178",
        "sorsolt_sorsz": 7,
        "szavlap_sorsz": 7,
        "neve": "NÉMETH-GÁL KLEOPÁTRA",
        "jlcs_kod": 0,
        "jelolo_szervezetek": [
          0
        ],
        "jlcs_nev": "Független",
        "allapot": "1",
        "allapot_valt": "2024-04-29T00:00:00+02:00"
      },
      {
        "ej_id": 95675,
        "valaltip": "3",
        "kpn_id": 5870469,
        "maz": "19",
        "taz": "178",
        "sorsolt_sorsz": 8,
        "szavlap_sorsz": 8,
        "neve": "GERENCSÉR LÁSZLÓ",
        "jlcs_kod": 0,
        "jelolo_szervezetek": [
          0
        ],
        "jlcs_nev": "Független",
        "allapot": "1",
        "allapot_valt": "2024-05-09T00:00:00+02:00"
      },
      {
        "ej_id": 93095,
        "valaltip": "3",
        "kpn_id": 1422180,
        "maz": "19",
        "taz": "178",
        "sorsolt_sorsz": 9,
        "szavlap_sorsz": 9,
        "neve": "MOLNÁR KÁROLY",
        "jlcs_kod": 0,
        "jelolo_szervezetek": [
          0
        ],
        "jlcs_nev": "Független",
        "allapot": "1",
        "allapot_valt": "2024-05-06T00:00:00+02:00"
      },
      {
        "ej_id": 100026,
        "valaltip": "3",
        "kpn_id": 4441751,
        "maz": "19",
        "taz": "178",
        "sorsolt_sorsz": 10,
        "szavlap_sorsz": 10,
        "neve": "MIHÁLYI CSONGOR",
        "jlcs_kod": 0,
        "jelolo_szervezetek": [
          0
        ],
        "jlcs_nev": "Független",
        "allapot": "1",
        "allapot_valt": "2024-05-06T00:00:00+02:00"
      },
      {
        "ej_id": 95832,
        "valaltip": "3",
        "kpn_id": 5361502,
        "maz": "19",
        "taz": "178",
        "sorsolt_sorsz": 11,
        "szavlap_sorsz": 11,
        "neve": "BIRKÁS DÁNIEL",
        "jlcs_kod": 0,
        "jelolo_szervezetek": [
          0
        ],
        "jlcs_nev": "Független",
        "allapot": "1",
        "allapot_valt": "2024-05-06T00:00:00+02:00"
      },
      {
        "ej_id": 102351,
        "valaltip": "3",
        "kpn_id": 7974368,
        "maz": "19",
        "taz": "178",
        "sorsolt_sorsz": 12,
        "szavlap_sorsz": 12,
        "neve": "BOTOS ANTAL",
        "jlcs_kod": 0,
        "jelolo_szervezetek": [
          0
        ],
        "jlcs_nev": "Független",
        "allapot": "1",
        "allapot_valt": "2024-04-29T00:00:00+02:00"
      },
      {
        "ej_id": 136238,
        "valaltip": "3",
        "kpn_id": 3558584,
        "maz": "19",
        "taz": "178",
        "sorsolt_sorsz": 13,
        "neve": "PAIZS MIKLÓS",
        "jlcs_kod": 2528,
        "jelolo_szervezetek": [
          1002
        ],
        "jlcs_nev": "MKKP",
        "allapot": "4",
        "allapot_valt": "2024-05-10T00:00:00+02:00"
      },
      {
        "ej_id": 91790,
        "valaltip": "3",
        "kpn_id": 5796840,
        "maz": "19",
        "taz": "178",
        "sorsolt_sorsz": 14,
        "neve": "SÁRVÁRI CSABA",
        "jlcs_kod": 0,
        "jelolo_szervezetek": [
          0
        ],
        "jlcs_nev": "Független",
        "allapot": "33",
        "allapot_valt": "2024-05-08T00:00:00+02:00"
      }
    ]
  }
}